certbot_dns_infoblox_universal/__init__.py
certbot_dns_infoblox_universal/dns_infoblox_universal.py
certbot_dns_infoblox_universal-0.1.0.dist-info/LICENSE
certbot_dns_infoblox_universal-0.1.0.dist-info/METADATA
certbot_dns_infoblox_universal-0.1.0.dist-info/WHEEL
certbot_dns_infoblox_universal-0.1.0.dist-info/entry_points.txt
certbot_dns_infoblox_universal-0.1.0.dist-info/top_level.txt
certbot_dns_infoblox_universal-0.1.0.dist-info/RECORD
