Metadata-Version: 2.2
Name: certbot-dns-infoblox-universal
Version: 0.1.0
Summary: Certbot plugin for Infoblox Universal DDI for DNS-01 Challenge
Home-page: https://github.com/infobloxopen/certbot-dns-infoblox-universal
Author: Infoblox
Classifier: Programming Language :: Python :: 3
Classifier: License :: OSI Approved :: Apache Software License
Classifier: Operating System :: OS Independent
Requires-Python: >=3.6
License-File: LICENSE
Requires-Dist: universal-ddi-python-client>=0.1.0
Requires-Dist: zope.interface>=7.1.1
Dynamic: author
Dynamic: classifier
Dynamic: description
Dynamic: description-content-type
Dynamic: home-page
Dynamic: requires-dist
Dynamic: requires-python
Dynamic: summary
